scuamate/__init__.py
scuamate/core.py
scuamate/version.py
scuamate/az/__init__.py
scuamate/az/azfuncs.py
scuamate/az/keyvault.py
scuamate/az/mssql.py
scuamate/gc/__init__.py
scuamate/gc/firestore.py
scuamate/gsattrack/__init__.py
scuamate/gsattrack/gsattrack.py
scuamate-0.0.4.dist-info/LICENSE.txt
scuamate-0.0.4.dist-info/METADATA
scuamate-0.0.4.dist-info/WHEEL
scuamate-0.0.4.dist-info/top_level.txt
scuamate-0.0.4.dist-info/RECORD
