Metadata-Version: 2.1
Name: scuamate
Version: 0.0.4
Summary: Some Cloud Utilities to Advance Monitoring of Animals and Their Ecosystems: utilities to help run, maintain, check, and back up the cloud infrastructure for next-generation wildlife monitoring projects (including SpaceCows and the National Koala Monitoring Program)
Home-page: https://github.com/NextGenEcologicalMonitoring/scuamate
Download-URL: https://github.com/NextGenEcologicalMonitoring/scuamate/archive/0.0.4.tar.gz
Author: CSIRO, Drew Ellison Terasaki Hart
Author-email: Drew.TerasakiHart@csiro.au
Project-URL: Source, https://github.com/NextGenEcologicalMonitoring/scuamate
Keywords: wildlife biodiversity ecological monitoring citizen community science
Classifier: Programming Language :: Python :: 3
Classifier: License :: OSI Approved :: MIT License
Classifier: Operating System :: OS Independent
Classifier: Intended Audience :: Science/Research
Requires-Python: >=3.9
License-File: LICENSE.txt
Requires-Dist: numpy
Requires-Dist: pandas
Requires-Dist: geopandas
Requires-Dist: matplotlib
Requires-Dist: python-dotenv
Requires-Dist: azure-identity
Requires-Dist: azure-keyvault
Requires-Dist: azure-functions
Requires-Dist: firebase-admin
Requires-Dist: pyodbc
Requires-Dist: scuamate
